robingame/__init__.py
robingame/animation.py
robingame/recording.py
robingame/sound.py
robingame/utils.py
robingame/__pycache__/__init__.cpython-310.pyc
robingame/__pycache__/animation.cpython-310.pyc
robingame/__pycache__/utils.cpython-310.pyc
robingame/examples/__init__.py
robingame/examples/font_sandbox.py
robingame/examples/hello_world.py
robingame/examples/particle_example.py
robingame/examples/__pycache__/__init__.cpython-310.pyc
robingame/examples/gui_examples/__init__.py
robingame/examples/gui_examples/coloured_button_effects.py
robingame/examples/gui_examples/complicated_on_press_hook.py
robingame/examples/gui_examples/on_press_event.py
robingame/examples/gui_examples/__pycache__/__init__.cpython-310.pyc
robingame/examples/gui_examples/__pycache__/coloured_button_effects.cpython-310.pyc
robingame/examples/gui_examples/assets/__init__.py
robingame/examples/gui_examples/assets/button-up.aseprite
robingame/examples/gui_examples/assets/button-up.png
robingame/examples/gui_examples/assets/flashybutton.aseprite
robingame/examples/gui_examples/assets/flashybutton.png
robingame/examples/gui_examples/assets/__pycache__/__init__.cpython-310.pyc
robingame/gui/__init__.py
robingame/gui/button.py
robingame/gui/menu.py
robingame/gui/__pycache__/__init__.cpython-310.pyc
robingame/gui/__pycache__/button.cpython-310.pyc
robingame/gui/__pycache__/menu.cpython-310.pyc
robingame/image/__init__.py
robingame/image/sprite_animation.py
robingame/image/utils.py
robingame/image/__pycache__/__init__.cpython-310.pyc
robingame/image/__pycache__/sprite_animation.cpython-310.pyc
robingame/image/__pycache__/utils.cpython-310.pyc
robingame/input/__init__.py
robingame/input/event.py
robingame/input/gamecube.py
robingame/input/keyboard.py
robingame/input/queue.py
robingame/input/visualization.py
robingame/input/__pycache__/__init__.cpython-310.pyc
robingame/input/__pycache__/event.cpython-310.pyc
robingame/input/__pycache__/gamecube.cpython-310.pyc
robingame-2.0.0.dist-info/LICENSE
robingame-2.0.0.dist-info/METADATA
robingame-2.0.0.dist-info/WHEEL
robingame-2.0.0.dist-info/top_level.txt
robingame-2.0.0.dist-info/RECORD
