Metadata-Version: 2.1
Name: robingame
Version: 2.0.0
Summary: Object-oriented tools for Pygame projects
Author-email: Robin Neville <robin.m.neville@gmail.com>
License: MIT License
Project-URL: Homepage,  https://github.com/binnev/robingame
Project-URL: Bug_Tracker, https://github.com/binnev/robingame/issues
Keywords: pygame,OOP
Classifier: Programming Language :: Python :: 3
Classifier: License :: OSI Approved :: MIT License
Classifier: Operating System :: OS Independent
Requires-Python: >=3.9
License-File: LICENSE
Requires-Dist: numpy >=1.0.0
Requires-Dist: pygame >=2.5.0
